angelsupport/GPTRequest.py
angelsupport/Logic.py
angelsupport/Model.py
angelsupport/Prompt.py
angelsupport/Tokenizer.py
angelsupport/__init__.py
angelsupport-0.0.8.dist-info/METADATA
angelsupport-0.0.8.dist-info/WHEEL
angelsupport-0.0.8.dist-info/top_level.txt
angelsupport-0.0.8.dist-info/RECORD
